joeutil/__init__.py
joeutil/adptools.py
example_package_joe-0.0.1.dist-info/LICENSE
example_package_joe-0.0.1.dist-info/METADATA
example_package_joe-0.0.1.dist-info/WHEEL
example_package_joe-0.0.1.dist-info/top_level.txt
example_package_joe-0.0.1.dist-info/RECORD
