Metadata-Version: 2.1
Name: example-package-joe
Version: 0.0.1
Summary: ADP Tools
Home-page: https://https://github.com/ksky1313/ADP
Author: joe
Author-email: kim_junhan@naver.com
Project-URL: Bug Tracker, https://github.com/ksky1313/ADP/issues
Classifier: Programming Language :: Python :: 3
Classifier: License :: OSI Approved :: MIT License
Classifier: Operating System :: OS Independent
Requires-Python: >=3.6
License-File: LICENSE
